{
  "publicPath": "/_nuxt/",
  "all": [
    "../server/index.spa.html",
    "../server/index.ssr.html",
    "03151dc.js",
    "13a938c.js",
    "38722db.js",
    "40d44b0.js",
    "6fb920e.js",
    "81f521b.js",
    "85175da.js",
    "LICENSES",
    "a1b5bbe.js",
    "a7bde6d.js",
    "be064b2.js",
    "c44ef7b.js"
  ],
  "initial": [
    "c44ef7b.js",
    "40d44b0.js",
    "a1b5bbe.js"
  ],
  "async": [
    "03151dc.js",
    "13a938c.js",
    "38722db.js",
    "6fb920e.js",
    "81f521b.js",
    "85175da.js",
    "a7bde6d.js",
    "be064b2.js"
  ],
  "modules": {
    "12954878": [
      5
    ],
    "16686639": [
      5
    ],
    "21330072": [
      5
    ],
    "21793458": [
      5
    ],
    "31655735": [
      5
    ],
    "33470412": [
      5
    ],
    "34701942": [
      5
    ],
    "36885819": [
      5
    ],
    "40617795": [
      3
    ],
    "57814186": [
      10
    ],
    "64861549": [
      5
    ],
    "91035072": [
      5
    ],
    "0cacf034": [
      10
    ],
    "783274dc": [
      5
    ],
    "53052a3d": [
      5
    ],
    "5f4ffa44": [
      5
    ],
    "77d04b7f": [
      5
    ],
    "636b4ee2": [
      5
    ],
    "216f71bd": [
      5
    ],
    "e894d750": [
      5
    ],
    "1aa3ef23": [
      5
    ],
    "bc64bf72": [
      5
    ],
    "adac8772": [
      5
    ],
    "0ac8d7cc": [
      5
    ],
    "d7bf8378": [
      5
    ],
    "4a5da780": [
      5
    ],
    "6b7b3066": [
      5
    ],
    "169e1ae2": [
      5
    ],
    "47741a7a": [
      5
    ],
    "0703e838": [
      5
    ],
    "7a28a3c3": [
      5
    ],
    "c97344f8": [
      5
    ],
    "61b9b63c": [
      5
    ],
    "060271d7": [
      5
    ],
    "4a574c89": [
      5
    ],
    "245f2a97": [
      5
    ],
    "305e4f1a": [
      10
    ],
    "4c883340": [
      10
    ],
    "55e5ac3a": [
      10
    ],
    "c4e13e48": [
      10
    ],
    "45f33129": [
      10
    ],
    "2646ef38": [
      10
    ],
    "4775da04": [
      10
    ],
    "634703f1": [
      10
    ],
    "e87c6afe": [
      10
    ],
    "3e9ac33e": [
      10
    ],
    "4a75673c": [
      10
    ],
    "24dcd1e0": [
      10
    ],
    "0466c600": [
      10
    ],
    "727aaa23": [
      10
    ],
    "98c134e4": [
      10
    ],
    "7e480324": [
      10
    ],
    "00ed0496": [
      10
    ],
    "68d706cc": [
      10
    ],
    "5d9189d8": [
      10
    ],
    "1afe345a": [
      5
    ],
    "20049d60": [
      5
    ],
    "0a0955cb": [
      5
    ],
    "200a876c": [
      5
    ],
    "eb8787ac": [
      5
    ],
    "38df8de2": [
      5
    ],
    "3116b302": [
      5
    ],
    "4b2d3eba": [
      5
    ],
    "48836a8b": [
      5
    ],
    "dbeff59e": [
      5
    ],
    "5cbfa2dc": [
      5
    ],
    "1ceb24da": [
      5
    ],
    "7d043514": [
      5
    ],
    "1df1de50": [
      5
    ],
    "0b40e8cc": [
      10
    ],
    "02956ddd": [
      5
    ],
    "82017b28": [
      5
    ],
    "feb4dcb6": [
      5
    ],
    "1514d91a": [
      5
    ],
    "0ae5975a": [
      5
    ],
    "4f78786c": [
      5
    ],
    "0c0cd1a1": [
      5
    ],
    "16503e26": [
      5
    ],
    "5d563a58": [
      5
    ],
    "4b0e5978": [
      5
    ],
    "779141d2": [
      5
    ],
    "32a59b2e": [
      5
    ],
    "a61d0086": [
      5
    ],
    "487ae47d": [
      5
    ],
    "efb8a2f0": [
      5
    ],
    "efc1ba5c": [
      5
    ],
    "58e5e08d": [
      5
    ],
    "38a5834e": [
      5
    ],
    "68e36f97": [
      5
    ],
    "efb4173a": [
      5
    ],
    "1dce848d": [
      5
    ],
    "3aab86c8": [
      5
    ],
    "d50ad510": [
      5
    ],
    "0228e396": [
      5
    ],
    "4c761cd6": [
      5
    ],
    "4f0eeaf7": [
      10
    ],
    "4d72ef47": [
      10
    ],
    "4d7ace9d": [
      5
    ],
    "24196f6a": [
      5
    ],
    "03450247": [
      5
    ],
    "0796fa54": [
      5
    ],
    "f20c3d8a": [
      5
    ],
    "5e7e64e3": [
      5
    ],
    "2815ef33": [
      5
    ],
    "739950ef": [
      5
    ],
    "076dd182": [
      5
    ],
    "c34f4f20": [
      5
    ],
    "8cfcfb30": [
      5
    ],
    "01fe44f8": [
      5
    ],
    "509af0b1": [
      5
    ],
    "4014dec7": [
      5
    ],
    "0555c3b4": [
      5
    ],
    "6a183757": [
      10
    ],
    "3b0d0a1e": [
      10
    ],
    "1384df9c": [
      5
    ],
    "c770c61c": [
      5
    ],
    "0c53e43b": [
      5
    ],
    "561c60ae": [
      5
    ],
    "5ec937e9": [
      5
    ],
    "56cc566a": [
      5
    ],
    "58d2b41a": [
      5
    ],
    "2bb7b09c": [
      5
    ],
    "0ef4be29": [
      5
    ],
    "587b938d": [
      5
    ],
    "246e4df6": [
      5
    ],
    "749d3e83": [
      5
    ],
    "7fb9d4b4": [
      5
    ],
    "1985b1ac": [
      5
    ],
    "5df7ce2d": [
      5
    ],
    "2fbf614a": [
      5
    ],
    "b17bec7c": [
      5
    ],
    "6465ad4b": [
      5
    ],
    "571fe37e": [
      5
    ],
    "53f09e84": [
      5
    ],
    "67a9fd2d": [
      5
    ],
    "718cff72": [
      5
    ],
    "347192aa": [
      5
    ],
    "5710fba9": [
      5
    ],
    "04866ee7": [
      10
    ],
    "3b348c85": [
      10
    ],
    "6da44073": [
      10
    ],
    "19fad8f3": [
      5
    ],
    "4e60aa0f": [
      5
    ],
    "463f034a": [
      5
    ],
    "cf3f1c70": [
      5
    ],
    "681fca83": [
      5
    ],
    "1554e4de": [
      5
    ],
    "644d3a20": [
      5
    ],
    "80abf376": [
      5
    ],
    "d7bc5fdc": [
      10
    ],
    "63ee7f53": [
      10
    ],
    "37b04d80": [
      5
    ],
    "76455ad7": [
      10
    ],
    "152ea498": [
      5
    ],
    "7a87b4b2": [
      10
    ],
    "42f20429": [
      10
    ],
    "3ca519c2": [
      5
    ],
    "22fc9fec": [
      10
    ],
    "5e032104": [
      10
    ],
    "6d3dafe4": [
      5
    ],
    "1aedc4a6": [
      5
    ],
    "df600c6e": [
      5
    ],
    "fe5b0888": [
      5
    ],
    "857885ce": [
      5
    ],
    "1d269eb4": [
      5
    ],
    "7d63b2fb": [
      5
    ],
    "ed0fd26a": [
      5
    ],
    "7b3f150c": [
      5
    ],
    "17409e08": [
      5
    ],
    "54e6b367": [
      5
    ],
    "92a45052": [
      5
    ],
    "4f99eb9a": [
      5
    ],
    "2b0e7413": [
      5
    ],
    "b171758a": [
      5
    ],
    "5801ec2f": [
      5
    ],
    "1eca62e0": [
      5
    ],
    "7758c68e": [
      5
    ],
    "65aa57c2": [
      5
    ],
    "456116b4": [
      5
    ],
    "7d30fb91": [
      5
    ],
    "6713f167": [
      5
    ],
    "596ee056": [
      10
    ],
    "e1b9a664": [
      10
    ],
    "7eb19297": [
      5
    ],
    "72c6dd92": [
      5
    ],
    "37a9f43e": [
      5
    ],
    "f76bbff0": [
      5
    ],
    "7690ed7c": [
      5
    ],
    "5e1c991f": [
      5
    ],
    "f060d956": [
      5
    ],
    "a32a0242": [
      5
    ],
    "917b9376": [
      5
    ],
    "99d29770": [
      5
    ],
    "4893a362": [
      5
    ],
    "968c8c3c": [
      5
    ],
    "3941f757": [
      5
    ],
    "c0a1234e": [
      5
    ],
    "1d9fca52": [
      10
    ],
    "fb035b92": [
      10
    ],
    "52da9f3a": [
      10
    ],
    "4d308fc3": [
      10
    ],
    "63d6a5c3": [
      10
    ],
    "5e60bd84": [
      5
    ],
    "16253e18": [
      5
    ],
    "3295ba48": [
      5
    ],
    "be60ef16": [
      5
    ],
    "418fd514": [
      5
    ],
    "fe0c368e": [
      5
    ],
    "722cad4a": [
      5
    ],
    "0a44b3e2": [
      5
    ],
    "3056f230": [
      5
    ],
    "0c296610": [
      5
    ],
    "ed73ec4a": [
      5
    ],
    "2bd7e71d": [
      5
    ],
    "52f3dd26": [
      5
    ],
    "cd21ac20": [
      5
    ],
    "0e74c5bd": [
      5
    ],
    "5c4fdbd4": [
      5
    ],
    "62c41100": [
      8
    ],
    "1e3dd85e": [
      8
    ],
    "b658646a": [
      8
    ],
    "357a19e8": [
      8
    ],
    "120bec9e": [
      4
    ],
    "68df8de4": [
      4
    ],
    "0d469f08": [
      8
    ],
    "765756d6": [
      8
    ],
    "23b2d8c4": [
      8
    ],
    "4bc7c49d": [
      8
    ],
    "7bbf7f07": [
      8
    ],
    "8f3bbaac": [
      8
    ],
    "ac98d530": [
      8
    ],
    "71a66552": [
      8
    ],
    "864286f2": [
      4
    ],
    "5b63d5f2": [
      4
    ],
    "5741ff02": [
      4
    ],
    "6afda60c": [
      11
    ],
    "3218ec25": [
      8
    ],
    "7df9906f": [
      8
    ],
    "eee7d060": [
      8
    ],
    "42ab6960": [
      8
    ],
    "b9096f10": [
      8
    ],
    "1e7f8c62": [
      8
    ],
    "9321e556": [
      8
    ],
    "0d248694": [
      8
    ],
    "28a417fa": [
      8
    ],
    "91ef328e": [
      8
    ],
    "d6d66570": [
      8
    ],
    "76ced22e": [
      8
    ],
    "cc328138": [
      8
    ],
    "63fc518a": [
      8
    ],
    "9ee8823c": [
      8
    ],
    "33ed9528": [
      8
    ],
    "354f9ea8": [
      8
    ],
    "83db3fc0": [
      8
    ],
    "2cf5aed3": [
      8
    ],
    "470b40d0": [
      8
    ],
    "c6256156": [
      8
    ],
    "c23492a8": [
      8
    ],
    "55385ea0": [
      8
    ],
    "d2521f06": [
      8
    ],
    "8acfed54": [
      8
    ],
    "5fca858c": [
      8
    ],
    "16ec60f4": [
      8
    ],
    "ce4eb7ce": [
      8
    ],
    "e56585f6": [
      8
    ],
    "2a3d35e0": [
      8
    ],
    "71eb87ca": [
      8
    ],
    "d5f52912": [
      8
    ],
    "15c11cc9": [
      8
    ],
    "4897cee6": [
      8
    ],
    "0d3454dd": [
      8
    ],
    "2e701c4c": [
      8
    ],
    "c97cc1b0": [
      8
    ],
    "1db44206": [
      8
    ],
    "4fe43207": [
      8
    ],
    "0c49af32": [
      8
    ],
    "084a6a68": [
      8
    ],
    "7cc4c819": [
      8
    ],
    "bd0b3c40": [
      8
    ],
    "7336698a": [
      8
    ],
    "35d89564": [
      8
    ],
    "d3d40ee0": [
      8
    ],
    "3a5b60b6": [
      8
    ],
    "7c04d23c": [
      8
    ],
    "1ce4beec": [
      8
    ],
    "62c10e78": [
      8
    ],
    "16ef144a": [
      8
    ],
    "1439c210": [
      8
    ],
    "2dc5c11a": [
      8
    ],
    "11f53b9b": [
      8
    ],
    "4e91f62c": [
      8
    ],
    "2f17d3cc": [
      8
    ],
    "0679f4d1": [
      2
    ],
    "6b17d8a8": [
      2
    ],
    "5cad2f0d": [
      2
    ],
    "237e732c": [
      2
    ],
    "0f993439": [
      2
    ],
    "47531ac6": [
      2
    ],
    "fa0d29e8": [
      2
    ],
    "516ef3cd": [
      2
    ],
    "25664b81": [
      2
    ],
    "2a829a24": [
      2
    ],
    "4ac89972": [
      2
    ],
    "dd39d1e2": [
      2
    ],
    "301ec9ad": [
      2
    ],
    "018b6530": [
      2
    ],
    "2b7e219e": [
      2
    ],
    "c78f060c": [
      4
    ],
    "3804d0ec": [
      4
    ],
    "7dbd6a9c": [
      4
    ],
    "06f15df0": [
      4
    ],
    "abc995f4": [
      4
    ],
    "25401a3a": [
      4
    ],
    "049a18f8": [
      11
    ],
    "081a09c0": [
      11
    ],
    "95a0cc0c": [
      11
    ],
    "16bf1d3c": [
      11
    ],
    "291a0bb4": [
      11
    ],
    "123db846": [
      11
    ],
    "1e477185": [
      12
    ],
    "a03f7c70": [
      12
    ],
    "6d986a72": [
      12
    ],
    "663cd874": [
      12
    ],
    "5b5c701b": [
      12
    ],
    "1ec4a478": [
      3
    ],
    "858eec5a": [
      3
    ],
    "04f25d7a": [
      3
    ],
    "90433ab4": [
      3
    ],
    "babdc184": [
      6
    ],
    "120c1e50": [
      6
    ],
    "ec21dd24": [
      6
    ],
    "4e228954": [
      6
    ],
    "3483b1c2": [
      6
    ],
    "339be008": [
      7
    ],
    "37f7ff42": [
      7
    ],
    "2366b4b8": [
      7
    ],
    "0105525d": [
      7
    ],
    "ff156a10": [
      7
    ]
  },
  "assetsMapping": {
    "bba68bf6": [
      "03151dc.js",
      "13a938c.js",
      "38722db.js",
      "6fb920e.js",
      "81f521b.js",
      "85175da.js",
      "a7bde6d.js",
      "be064b2.js"
    ],
    "085a35c4": [
      "40d44b0.js"
    ],
    "1a3ae26b": [
      "a1b5bbe.js"
    ],
    "6fca0322": [
      "c44ef7b.js"
    ]
  }
}